smskit
tests
