Metadata-Version: 1.0
Name: smskit
Version: 0.0.7
Summary: Abstack sms utils component.
Home-page: http://www.abstack.com/
Author: abstack
Author-email: mzj@abstack.com
License: UNKNOWN
Keywords: smskit is a sms utils!
Platform: UNKNOWN
